terraria_xbox360_player_api/__init__.py
terraria_xbox360_player_api/terraria_xbox360_player_api.py
terraria_xbox360_player_api-1.0.6.dist-info/LICENSE
terraria_xbox360_player_api-1.0.6.dist-info/METADATA
terraria_xbox360_player_api-1.0.6.dist-info/WHEEL
terraria_xbox360_player_api-1.0.6.dist-info/top_level.txt
terraria_xbox360_player_api-1.0.6.dist-info/RECORD
