Metadata-Version: 2.1
Name: terraria-xbox360-player-api
Version: 1.0.6
Summary: API for reading and modifying xbox 360 terraria player files.
Home-page: https://gitlab.com/fkwilczek/terraria-xbox360-player-api
Author: Filip K
Author-email: fkwilczek@gmail.com
License: GNU General Public License v3 (GPLv3)
Platform: UNKNOWN
Classifier: Programming Language :: Python :: 3
Classifier: Operating System :: OS Independent
Classifier: License :: OSI Approved :: GNU General Public License v3 (GPLv3)
License-File: LICENSE
Requires-Dist: bitarray
Requires-Dist: binary-rw
Requires-Dist: terraria-apis-objects
